drf_hal_json/__init__.py
drf_hal_json/pagination.py
drf_hal_json/parsers.py
drf_hal_json/renderers.py
drf_hal_json/serializers.py
drf_hal_json/views.py
drf_hal_json-0.10.0.dist-info/LICENSE.md
drf_hal_json-0.10.0.dist-info/METADATA
drf_hal_json-0.10.0.dist-info/WHEEL
drf_hal_json-0.10.0.dist-info/top_level.txt
drf_hal_json-0.10.0.dist-info/RECORD
