Metadata-Version: 2.1
Name: drf-hal-json
Version: 0.10.0
Summary: Extension for Django REST Framework 3 which allows for using content-type application/hal-json
Home-page: https://github.com/seebass/drf-hal-json
Author: Sebastian Bredehöft
Author-email: bredehoeft.sebastian@gmail.com
License: MIT
Platform: UNKNOWN
Classifier: Development Status :: 4 - Beta
Classifier: Environment :: Web Environment
Classifier: Framework :: Django
Classifier: Intended Audience :: Developers
Classifier: License :: OSI Approved :: MIT License
Classifier: Operating System :: OS Independent
Classifier: Programming Language :: Python
Classifier: Programming Language :: Python :: 3
Classifier: Topic :: Internet :: WWW/HTTP
Requires-Dist: django (>=2.0)
Requires-Dist: djangorestframework (>=3.10.0)
Requires-Dist: drf-nested-fields (>=0.9.0)
